odoo8_addon_shell-8.0.1.0.0-py2.7-nspkg.pth
odoo_addons/shell/__openerp__.py
odoo_addons/shell/__init__.py
odoo_addons/shell/README.rst
odoo_addons/shell/cli/shell.py
odoo_addons/shell/cli/__init__.py
odoo_addons/shell/static/description/icon.png
odoo8_addon_shell-8.0.1.0.0.dist-info/top_level.txt
odoo8_addon_shell-8.0.1.0.0.dist-info/WHEEL
odoo8_addon_shell-8.0.1.0.0.dist-info/RECORD
odoo8_addon_shell-8.0.1.0.0.dist-info/metadata.json
odoo8_addon_shell-8.0.1.0.0.dist-info/DESCRIPTION.rst
odoo8_addon_shell-8.0.1.0.0.dist-info/METADATA
odoo8_addon_shell-8.0.1.0.0.dist-info/namespace_packages.txt
